decapi/DecApiError.py
decapi/Defaults.py
decapi/EmptyClass.py
decapi/Voice.py
decapi/__init__.py
decapi/decapi.py
decapi/dv.py
decapi/init.py
decapi/init2.py
decapi/say.py
decapi/sayAsync.py
decapi/useVoice.py
decapi-1.0.4.dist-info/LICENSE
decapi-1.0.4.dist-info/METADATA
decapi-1.0.4.dist-info/WHEEL
decapi-1.0.4.dist-info/top_level.txt
decapi-1.0.4.dist-info/RECORD
