Metadata-Version: 2.1
Name: decapi
Version: 1.0.4
Summary: An API for DECTalk
Author-email: GDPlayer1035 <someguyyounotknow@gmail.com>
License: MIT
Classifier: Programming Language :: Python :: 3
Classifier: License :: OSI Approved :: MIT License
Classifier: Operating System :: OS Independent
Requires-Python: >=3.7
License-File: LICENSE
Requires-Dist: asyncio
